pipPractice/TestJson.py
pipPractice/Thread.py
pipPractice/__init__.py
pipPractice/decorator.py
pipPractice/first_class_function.py
pipPractice/restAPIweather.py
pipPractice-1.0.1.dist-info/METADATA
pipPractice-1.0.1.dist-info/WHEEL
pipPractice-1.0.1.dist-info/top_level.txt
pipPractice-1.0.1.dist-info/RECORD
